FunFun/FunFun.py
FunFun/__init__.py
FunFun/data/CONCATENATE_base.tsv
FunFun/data/ITS1_base.tsv
FunFun/data/ITS2_base.tsv
FunFun/data/functionality.tsv
FunFun/example/its2.fasta
FunFun/src/Get_distance.py
FunFun/src/Get_functional.py
FunFun-0.1.15.dist-info/LICENSE
FunFun-0.1.15.dist-info/METADATA
FunFun-0.1.15.dist-info/WHEEL
FunFun-0.1.15.dist-info/entry_points.txt
FunFun-0.1.15.dist-info/top_level.txt
FunFun-0.1.15.dist-info/RECORD
